ezsmdeploy/__init__.py
ezsmdeploy/data/Dockerfile
ezsmdeploy/data/Dockerfile_flask
ezsmdeploy/data/build-docker.sh
ezsmdeploy/data/conversation.py
ezsmdeploy/data/cost.csv
ezsmdeploy/data/dockerd-entrypoint.py
ezsmdeploy/data/instancetypes.csv
ezsmdeploy/data/model_handler.py
ezsmdeploy/data/nginx.conf
ezsmdeploy/data/predictor.py
ezsmdeploy/data/serve
ezsmdeploy/data/smlocust.py
ezsmdeploy/data/train
ezsmdeploy/data/wsgi.py
ezsmdeploy-2.24.0.dist-info/METADATA
ezsmdeploy-2.24.0.dist-info/WHEEL
ezsmdeploy-2.24.0.dist-info/top_level.txt
ezsmdeploy-2.24.0.dist-info/RECORD
