Metadata-Version: 2.1
Name: ezsmdeploy
Version: 2.24.0
Summary: Amazon SageMaker and Bedrock custom model deployments made easy
Home-page: https://pypi.python.org/pypi/ezsmdeploy
Author: Shreyas Subramanian
Author-email: subshrey@amazon.com
License: MIT
Classifier: Development Status :: 5 - Production/Stable
Classifier: Intended Audience :: Developers
Classifier: Natural Language :: English
Classifier: License :: OSI Approved :: Apache Software License
Classifier: Programming Language :: Python
Requires-Dist: sagemaker==2.238.0
Requires-Dist: yaspin==0.16.0
Requires-Dist: shortuuid==1.0.1
Requires-Dist: sagemaker-studio-image-build==0.5.0
Requires-Dist: boto3>=1.14.12
Requires-Dist: huggingface-hub==0.28.1
Provides-Extra: locust
Requires-Dist: locustio==0.14.5; extra == "locust"
Provides-Extra: transformers
Requires-Dist: transformers==4.49.0; extra == "transformers"
Requires-Dist: peft==0.14.0; extra == "transformers"
